whistling_duck/__init__.py
whistling_duck/main.py
whistlingduck/__init__.py
whistlingduck/main.py
whistlingduck/analyzers/__init__.py
whistlingduck/analyzers/standard_deviation.py
whistlingduck/analyzers/sum.py
whistlingduck/analyzers/unique_value_ratio.py
whistlingduck/analyzers/uniqueness.py
whistlingduck/documentation/csv_into_table_doc.py
whistlingduck/read/__init__.py
whistlingduck/read/csv_into_table.py
whistlingduck-1.0.dist-info/LICENSE
whistlingduck-1.0.dist-info/METADATA
whistlingduck-1.0.dist-info/WHEEL
whistlingduck-1.0.dist-info/top_level.txt
whistlingduck-1.0.dist-info/RECORD
